mspec/__init__.py
mspec/__main__.py
mspec/markup.py
mspec/data/_draft_cms.yaml
mspec/data/_draft_core.yaml
mspec/data/_draft_sample.yaml
mspec/data/functions.json
mspec/data/hello-world-page.json
mspec/data/my-sample-store.yaml
mspec/data/return-types.json
mspec/data/simple-social-network.yaml
mspec/data/test-gen.yaml
mspec/data/test-page.json
mspec-0.0.10a0.dist-info/licenses/LICENSE
mtemplate/__init__.py
mtemplate/__main__.py
mtemplate/browser1.py
mtemplate/py.py
mtemplate/.cache/browser1/.gitignore.jinja2
mtemplate/.cache/browser1/README.md.jinja2
mtemplate/.cache/browser1/macro.json
mtemplate/.cache/browser1/package-lock.json.jinja2
mtemplate/.cache/browser1/package.json.jinja2
mtemplate/.cache/browser1/playwright.config.js.jinja2
mtemplate/.cache/browser1/template_paths.json
mtemplate/.cache/browser1/srv/index.html.jinja2
mtemplate/.cache/browser1/srv/index.js.jinja2
mtemplate/.cache/browser1/srv/style.css.jinja2
mtemplate/.cache/browser1/srv/auth/create-user.html.jinja2
mtemplate/.cache/browser1/srv/auth/login.html.jinja2
mtemplate/.cache/browser1/srv/auth/user-account.html.jinja2
mtemplate/.cache/browser1/srv/template-module/index.html.jinja2
mtemplate/.cache/browser1/srv/template-module/index.js.jinja2
mtemplate/.cache/browser1/srv/template-module/multi-model/index.html.jinja2
mtemplate/.cache/browser1/srv/template-module/multi-model/index.js.jinja2
mtemplate/.cache/browser1/srv/template-module/multi-model/instance.html.jinja2
mtemplate/.cache/browser1/srv/template-module/single-model/index.html.jinja2
mtemplate/.cache/browser1/srv/template-module/single-model/index.js.jinja2
mtemplate/.cache/browser1/srv/template-module/single-model/instance.html.jinja2
mtemplate/.cache/browser1/tests/core/auth.spec.js.jinja2
mtemplate/.cache/browser1/tests/core/user.setup.ts.jinja2
mtemplate/.cache/browser1/tests/template-module/multiModel.spec.js.jinja2
mtemplate/.cache/browser1/tests/template-module/singleModel.spec.js.jinja2
mtemplate/.cache/py/.env.example.jinja2
mtemplate/.cache/py/.gitignore.jinja2
mspec-0.0.10a0.dist-info/METADATA
mspec-0.0.10a0.dist-info/WHEEL
mspec-0.0.10a0.dist-info/top_level.txt
mspec-0.0.10a0.dist-info/RECORD
