Metadata-Version: 2.4
Name: mspec
Version: 0.0.10a0
Summary: mspec application generator and browsing protocol
Author-email: Brad Corlett <brad.corlett@gmail.com>
License-Expression: MIT
Project-URL: Homepage, https://github.com/medium-tech/mspec
Project-URL: Documentation, https://github.com/medium-tech/mspec/blob/main/README.md
Project-URL: Repository, https://github.com/medium-tech/mspec
Requires-Python: >=3.7
License-File: LICENSE
Requires-Dist: pyyaml==6.0.2
Requires-Dist: Jinja2==3.1.4
Dynamic: license-file
